datasette_leaflet_geojson/__init__.py
datasette_leaflet_geojson/static/datasette-leaflet-geojson.js
datasette_leaflet_geojson-0.8.2.dist-info/METADATA
datasette_leaflet_geojson-0.8.2.dist-info/WHEEL
datasette_leaflet_geojson-0.8.2.dist-info/entry_points.txt
datasette_leaflet_geojson-0.8.2.dist-info/top_level.txt
datasette_leaflet_geojson-0.8.2.dist-info/RECORD
