Metadata-Version: 2.1
Name: datasette-leaflet-geojson
Version: 0.8.2
Summary: A Datasette plugin that renders GeoJSON columns using Leaflet
Home-page: https://github.com/simonw/datasette-leaflet-geojson
Author: Simon Willison
License: Apache License, Version 2.0
Requires-Dist: datasette >=0.54
Requires-Dist: datasette-leaflet >=0.2
Provides-Extra: test
Requires-Dist: pytest ; extra == 'test'
Requires-Dist: pytest-asyncio ; extra == 'test'
